setup.py
springc_utils/__init__.py
springc_utils/data_convert.py
springc_utils/files.py
springc_utils/imgs.py
springc_utils/ious.py
springc_utils/logging.py
springc_utils/time_decorator.py
springc_utils.egg-info/PKG-INFO
springc_utils.egg-info/SOURCES.txt
springc_utils.egg-info/dependency_links.txt
springc_utils.egg-info/requires.txt
springc_utils.egg-info/top_level.txt