Metadata-Version: 2.1
Name: springc_utils
Version: 0.0.5
Summary: A successful sign for python setup
Home-page: https://github.com/SpringCCC/myutils
Author: SpringC
Author-email: jiqimaohw@gmail.com
License: MIT Licence
Keywords: pip,SpringC
Platform: any
Requires-Dist: numpy
